{
  "courses": {
    "nlp_expert": "https://t.me/+puh4LqwHfpk5OWI0",
    "nlp_beginner": "https://t.me/+_423nVlNiIFmNDU0",
    "nlp_intermediate": "https://t.me/+d_hBzkmeESQ5MWZk"
  },
  "materials": {
    "year4_sem1_neural_networks": "https://t.me/+7aZDu4oeoS5hODk0",
    "year4_sem1_smart_search": "https://t.me/+PMc5Ny9SdGI2MDBk",
    "year4_sem1_multimedia": "https://t.me/+fglYFM01ODc4NTc0",
    "year4_sem1_python": "https://t.me/+8dJhXxqTEndhNTA8",
    "year4_sem1_concurrent": "https://t.me/+bTYcNAe-PQRkZDE8",
    "year3_sem1_os": "https://t.me/+EN9jjyzr2_swYTk0",
    "year3_sem2_ai_principles": "https://t.me/+P8zKygmSLaNhZGQ8",
    "year3_sem1_algorithms": "https://t.me/+gvwFJhMq5cFiNDM8"
  }
}
